{
    "title": "Class: Vector",
    "intro": "The Vector class specifies a Vector, or point, on the canvas. It has a few methods for translating, scaling, roatating, etc the Vector.",
    "main": {
        "name": "Vector",
        "type": "constructor",
        "description": "The main Vector constructor. Calling without arguments returns a Vector at (0,0).",
        "arguments": [
            {
                "name": "x",
                "type": "number",
                "description": "The x-coordinate of the Vector",
                "default": 0,
                "optional": true
            },
            {
                "name": "y",
                "type": "number",
                "description": "The y-coordinate of the Vector",
                "default": 0,
                "optional": true
            }
        ],
        "children": [
            {
                "name": "copy",
                "type": "method",
                "description": "Copy the values of the other Vector to this one. Returns this Vector.",
                "return": "Vector",
                "arguments": [
                    {
                        "name": "other",
                        "type": "Vector",
                        "description": "The Vector to copy the values from."
                    }
                ]
            },
            {
                "name": "clone",
                "type": "method",
                "description": "Clone this Vector to a new one, and return that one.",
                "return": "Vector"
            },
            {
                "name": "perpendicular",
                "alias": ["perp"],
                "type": "method",
                "description": "Change this Vector to be perpendicular to the original.",
                "return": "Vector"
            },
            {
                "name": "reverse",
                "type": "method",
                "description": "Reverse this Vector.",
                "return": "Vector"
            },
            {
                "name": "normalize",
                "type": "method",
                "description": "Normalize this Vector, i.e. make it unit-lengthed.",
                "return": "Vector"
            },
            {
                "name": "add",
                "type": "method",
                "description": "Add the other vector to this one.",
                "return": "Vector",
                "arguments": [
                    {
                        "name": "other",
                        "type": "Vector",
                        "description": "The Vector to add."
                    }
                ]
            },
            {
                "name": "subtract",
                "alias": ["sub"],
                "type": "method",
                "desription": "Subtract the other Vector from this one.",
                "return": "Vector",
                "arguments": [
                    {
                        "name": "other",
                        "type": "Vector",
                        "description": "The Vector to subtract from the original."
                    }
                ]
            },
            {
                "name": "scale",
                "type": "method",
                "description": "Scale the Vector by the given factors, in x and y directions.",
                "return": "Vector",
                "arguments": [
                    {
                        "name": "x",
                        "type": "number",
                        "description": "The factor by which to scale the Vector in the x direction."
                    },
                    {
                        "name": "y",
                        "type": "number",
                        "description": "The factor by which to scale the Vector in the y direction."
                    }
                ]
            },
            {
                "name": "rotateP",
                "alias": ["rotate"],
                "type": "method",
                "description": "Rotate this Vector (counter-clockwise) around the given point.",
                "return": "Vector",
                "arguments": [
                    {
                        "name": "angle",
                        "type": "number",
                        "description": "The angle by which to rotate, in radians."
                    },
                    {
                        "name": "point",
                        "type": "Vector",
                        "description": "The point around which to rotate."
                    }
                ]
            },
            {
                "name": "project",
                "type": "method",
                "description": "Project this Vector onto another one.",
                "return": "Vector",
                "arguments": [
                    {
                        "name": "other",
                        "type": "Vector",
                        "description": "The Vector to project the original on."
                    }
                ]
            },
            {
                "name": "reflect",
                "type": "method",
                "description": "Reflect this Vector on an arbitrary axis.",
                "return": "Vector",
                "arguments": [
                    {
                        "name": "axis",
                        "type": "Vector",
                        "description": "The axis to reflect on."
                    }
                ]
            },
            {
                "name": "dot",
                "type": "method",
                "description": "Get the dot product of this Vector with another one.",
                "return": "number",
                "arguments": [
                    {
                        "name": "other",
                        "type": "Vector",
                        "description": "The second Vector."
                    }
                ]
            },
            {
                "name": "len2",
                "type": "method",
                "description": "Get the squared length of this Vector.",
                "return": "number"
            },
            {
                "name": "len",
                "type": "method",
                "description": "Get the length of this Vector.",
                "return": "number"
            }
        ]
    }
}